fasrat/__init__.py
fasrat/_version.py
fasrat/cli.py
fasrat/constants.py
fasrat/geometry.py
fasrat/process.py
fasrat-1.4.0.dist-info/licenses/LICENSE
fasrat-1.4.0.dist-info/METADATA
fasrat-1.4.0.dist-info/WHEEL
fasrat-1.4.0.dist-info/entry_points.txt
fasrat-1.4.0.dist-info/top_level.txt
fasrat-1.4.0.dist-info/RECORD
