Metadata-Version: 2.4
Name: fasrat
Version: 1.4.0
Summary: Fast Area-weighted Spatial ReAggregation Tool - Compute area-weighted intersection weights between shapefile geometries and raster pixels
Author: Jong Woo Nam
License: MIT
Project-URL: Homepage, https://github.com/njw0709/FASRAT
Project-URL: Repository, https://github.com/njw0709/FASRAT
Project-URL: Documentation, https://github.com/njw0709/FASRAT#readme
Keywords: gis,spatial,raster,shapefile,aggregation,geospatial
Classifier: Development Status :: 4 - Beta
Classifier: Intended Audience :: Science/Research
Classifier: License :: OSI Approved :: MIT License
Classifier: Programming Language :: Python :: 3
Classifier: Programming Language :: Python :: 3.9
Classifier: Programming Language :: Python :: 3.10
Classifier: Programming Language :: Python :: 3.11
Classifier: Programming Language :: Python :: 3.12
Classifier: Topic :: Scientific/Engineering :: GIS
Requires-Python: >=3.9
License-File: LICENSE
Requires-Dist: click>=8.1.7
Requires-Dist: geopandas>=1.0.1
Requires-Dist: numpy>=2.0.2
Requires-Dist: pandas>=2.3.3
Requires-Dist: pyarrow>=21.0.0
Requires-Dist: rasterio>=1.4.3
Requires-Dist: shapely>=2.0.7
Requires-Dist: tqdm>=4.67.1
Dynamic: license-file
